my_sdk/__init__.py
my_sdk/admin.py
my_sdk/auth.py
my_sdk/base.py
my_sdk/bots.py
my_sdk/client.py
my_sdk/exceptions.py
my_sdk/media.py
my_sdk/network.py
my_sdk/system.py
my_sdk/templates.py
my_sdk/user.py
my_sdk/visual_editor.py
tests/__init__.py
tests/test_base.py
tests/test_client.py
tests/test_exceptions.py
tests/test_network.py
low_code_api_lib_sdk-0.1.1.dist-info/METADATA
low_code_api_lib_sdk-0.1.1.dist-info/WHEEL
low_code_api_lib_sdk-0.1.1.dist-info/top_level.txt
low_code_api_lib_sdk-0.1.1.dist-info/RECORD
